robota_core/__init__.py
robota_core/attendance.py
robota_core/ci.py
robota_core/commit.py
robota_core/config_readers.py
robota_core/data_server.py
robota_core/github_tools.py
robota_core/gitlab_tools.py
robota_core/issue.py
robota_core/logic.py
robota_core/merge_request.py
robota_core/remote_provider.py
robota_core/repository.py
robota_core/string_processing.py
robota_core/commit_visualisation/commit_visualisation.py
robota_core/commit_visualisation/test/test_commit_visualisation.py
robota_core/tests/test_config_readers.py
robota_core/tests/test_gitlab_tools.py
robota_core/tests/test_issue_handling.py
robota_core/tests/test_robota_tools.py
robota_core-2.3.0.dist-info/LICENCE
robota_core-2.3.0.dist-info/METADATA
robota_core-2.3.0.dist-info/WHEEL
robota_core-2.3.0.dist-info/top_level.txt
robota_core-2.3.0.dist-info/RECORD
