Metadata-Version: 2.1
Name: robota-core
Version: 2.3.0
Summary: A package to retrieve version controlled software projects from GitHub and GitLab, for further analysis.
Author-email: University of Manchester <suzanne.m.embury@manchester.ac.uk>
Project-URL: Homepage, https://gitlab.cs.man.ac.uk/institute-of-coding/robota-core
Project-URL: Issues, https://gitlab.cs.man.ac.uk/institute-of-coding/robota-core/-/issues
Classifier: Programming Language :: Python :: 3
Classifier: License :: OSI Approved :: MIT License
Requires-Python: >=3.8
License-File: LICENCE
Requires-Dist: requests
Requires-Dist: jinja2
Requires-Dist: python-gitlab ==2.10.1
Requires-Dist: PyYaml >=5.1
Requires-Dist: pytest
Requires-Dist: gitpython
Requires-Dist: python-jenkins
Requires-Dist: python-dateutil
Requires-Dist: bleach
Requires-Dist: Markdown
Requires-Dist: PyGithub
Requires-Dist: loguru
Requires-Dist: dateparser
